[
  {
    "footer": "",
    "name": "",
    "header": "",
    "id": null
  },
  {
    "footer": "footer2DIa82",
    "name": "name1q60bq",
    "header": "headernIguEFi23ML0JATqC",
    "id": null
  },
  {
    "footer": "footerSZs3jw0rg4KGtM",
    "name": "nameLJp0GR2",
    "header": "headerD12uxs",
    "id": null
  },
  {
    "footer": "footerQi5nmZd7PDuIhoPY",
    "name": "nameh0",
    "header": "headerCOdoFq",
    "id": null
  },
  {
    "footer": "footerlu3cqq",
    "name": "name5QEH",
    "header": "headeriaySJ9Ta8ysYKZ",
    "id": null
  },
  {
    "footer": "footerUDRXO5oh4JUj5he",
    "name": "namerQLjjukS",
    "header": "headernf",
    "id": null
  }
]